baml_ffi-0.1.0.dist-info/METADATA
baml_ffi-0.1.0.dist-info/WHEEL
baml_ffi-0.1.0.dist-info/license_files/LICENSE
baml_ffi/__init__.py
baml_ffi/baml_ffi.abi3.so
baml_ffi-0.1.0.dist-info/RECORD
