Metadata-Version: 2.3
Name: baml-ffi
Version: 0.1.0
License-File: LICENSE
Summary: BAML python bindings
Author: Boundary <contact@boundaryml.com>
Author-email: Boundary <contact@boundaryml.com>
